labelocr/__init__.py
labelocr/label_ocr.ui
labelocr/labelocrapp.py
labelocr/verify_ocr_app.py
labelocr/icons/icon.png
labelocr-1.2.2.dist-info/LICENSE
labelocr-1.2.2.dist-info/METADATA
labelocr-1.2.2.dist-info/WHEEL
labelocr-1.2.2.dist-info/entry_points.txt
labelocr-1.2.2.dist-info/top_level.txt
labelocr-1.2.2.dist-info/RECORD
