Metadata-Version: 2.1
Name: labelocr
Version: 1.2.2
Summary: Image OCR Annotation with Python
Home-page: https://github.com/tienthienhd/labelocr
Author: Thien NT
Author-email: tienthienhd@gmail.com
License: LICENSE
Keywords: Image Annotation,Machine Learning,OCR
Platform: UNKNOWN
Classifier: Programming Language :: Python :: 3.6
Classifier: Programming Language :: Python :: 3.7
Requires-Dist: opencv-python
Requires-Dist: numpy
Requires-Dist: Pillow (==8.0.1)
Requires-Dist: Deprecated
Requires-Dist: pygubu
Requires-Dist: pandas
